classes/__init__.py
classes/_registry.py
classes/_typeclass.py
classes/contrib/__init__.py
classes/contrib/mypy/__init__.py
classes/contrib/mypy/classes_plugin.py
classes/contrib/mypy/features/__init__.py
classes/contrib/mypy/features/associated_type.py
classes/contrib/mypy/features/supports.py
classes/contrib/mypy/features/typeclass.py
classes/contrib/mypy/semanal/__init__.py
classes/contrib/mypy/semanal/variadic_generic.py
classes/contrib/mypy/typeops/__init__.py
classes/contrib/mypy/typeops/call_signatures.py
classes/contrib/mypy/typeops/fallback.py
classes/contrib/mypy/typeops/inference.py
classes/contrib/mypy/typeops/instance_context.py
classes/contrib/mypy/typeops/instance_type_args.py
classes/contrib/mypy/typeops/mro.py
classes/contrib/mypy/typeops/type_loader.py
classes/contrib/mypy/typeops/type_queries.py
classes/contrib/mypy/validation/__init__.py
classes/contrib/mypy/validation/validate_associated_type.py
classes/contrib/mypy/validation/validate_instance/__init__.py
classes/contrib/mypy/validation/validate_instance/validate_instance_args.py
classes/contrib/mypy/validation/validate_instance/validate_runtime.py
classes/contrib/mypy/validation/validate_instance/validate_signature.py
classes/contrib/mypy/validation/validate_supports.py
classes/contrib/mypy/validation/validate_typeclass_def.py
classes/py.typed
classes-0.4.0.dist-info/LICENSE
classes-0.4.0.dist-info/WHEEL
classes-0.4.0.dist-info/METADATA
classes-0.4.0.dist-info/RECORD
